<?xml version="1.0" encoding="utf-8"?>
<EntityRelationships xmlns:xsi="http://www.w3.org/2001/XMLSchema-instance">
  <EntityRelationship Name="business_unit_tlc_consult" />
  <EntityRelationship Name="business_unit_tlc_scenario" />
  <EntityRelationship Name="lk_tlc_consult_createdby" />
  <EntityRelationship Name="lk_tlc_consult_modifiedby" />
  <EntityRelationship Name="lk_tlc_scenario_createdby" />
  <EntityRelationship Name="lk_tlc_scenario_modifiedby" />
  <EntityRelationship Name="owner_tlc_consult" />
  <EntityRelationship Name="owner_tlc_scenario" />
  <EntityRelationship Name="team_tlc_consult" />
  <EntityRelationship Name="team_tlc_scenario" />
  <EntityRelationship Name="tlc_Consult_aaduser_contributor" />
  <EntityRelationship Name="tlc_Consult_tlc_Scenario_tlc_Scenario" />
  <EntityRelationship Name="tlc_Scenario_aaduser_aaduser" />
  <EntityRelationship Name="tlc_Scenario_ScenarioSponsorId_SystemUser" />
  <EntityRelationship Name="tlc_tlc_scenario_tlc_AssignedCoach_system" />
  <EntityRelationship Name="user_tlc_consult" />
  <EntityRelationship Name="user_tlc_scenario" />
</EntityRelationships>